LICENSE
README
setup.py
morbid/__init__.py
morbid/error.py
morbid/messagequeue.py
morbid/morbid.py
morbid/mqsecurity.py
morbid/restq.py
morbid.egg-info/PKG-INFO
morbid.egg-info/SOURCES.txt
morbid.egg-info/dependency_links.txt
morbid.egg-info/entry_points.txt
morbid.egg-info/requires.txt
morbid.egg-info/top_level.txt
morbid/sample_auth/__init__.py
morbid/sample_auth/mqanyconf.py
morbid/sample_auth/mqfileconf.py
morbid/sample_auth/mqtestconf.py
morbid/sample_auth/userIdFile.txt
morbid/tests/__init__.py
morbid/tests/restq_dummy_daemon.py
morbid/tests/test_messagequeue.py
morbid/tests/test_morbid.py
morbid/tests/test_mqanyconf.py
morbid/tests/test_mqfileconf.py