Metadata-Version: 1.0
Name: morbid
Version: 0.8.6.1
Summary: A Twisted-based publish/subscribe messaging server that uses the STOMP protocol
Home-page: UNKNOWN
Author: Michael Carter
Author-email: CarterMichael@gmail.com
License: MIT License
Platform: UNKNOWN
Classifier: Development Status :: 4 - Beta
Classifier: Environment :: Console
Classifier: Intended Audience :: Developers
Classifier: License :: OSI Approved :: MIT License
Classifier: Operating System :: OS Independent
Classifier: Programming Language :: Python
Classifier: Topic :: Software Development :: Libraries :: Python Modules
